{
  "badge": {
    "color": {
      "primary": {
        "300": {
          "filled": {
            "background-color": {
              "attributes": {
                "category": "color"
              },
              "value": "{color.primary.300}"
            },
            "border-color": {
              "attributes": {
                "category": "color"
              },
              "value": "{color.primary.300}"
            },
            "color": {
              "attributes": {
                "category": "color"
              },
              "value": "{color.primary.800}"
            }
          },
          "outlined": {
            "background-color": {
              "attributes": {
                "category": "color"
              },
              "value": "{color.neutral.transparent}"
            },
            "border-color": {
              "attributes": {
                "category": "color"
              },
              "value": "{color.primary.300}"
            },
            "color": {
              "attributes": {
                "category": "color"
              },
              "value": "{color.primary.800}"
            }
          },
          "text": {
            "background-color": {
              "attributes": {
                "category": "color"
              },
              "value": "{color.neutral.transparent}"
            },
            "border-color": {
              "attributes": {
                "category": "color"
              },
              "value": "{color.neutral.transparent}"
            },
            "color": {
              "attributes": {
                "category": "color"
              },
              "value": "{color.primary.800}"
            }
          }
        }
      },
      "error": {
        "filled": {
          "background-color": {
            "attributes": {
              "category": "color"
            },
            "value": "{color.error.200}"
          },
          "border-color": {
            "attributes": {
              "category": "color"
            },
            "value": "{color.error.200}"
          },
          "color": {
            "attributes": {
              "category": "color"
            },
            "value": "{color.error.800}"
          }
        },
        "outlined": {
          "background-color": {
            "attributes": {
              "category": "color"
            },
            "value": "{color.neutral.transparent}"
          },
          "border-color": {
            "attributes": {
              "category": "color"
            },
            "value": "{color.error.200}"
          },
          "color": {
            "attributes": {
              "category": "color"
            },
            "value": "{color.error.800}"
          }
        },
        "text": {
          "background-color": {
            "attributes": {
              "category": "color"
            },
            "value": "{color.neutral.transparent}"
          },
          "border-color": {
            "attributes": {
              "category": "color"
            },
            "value": "{color.neutral.transparent}"
          },
          "color": {
            "attributes": {
              "category": "color"
            },
            "value": "{color.error.800}"
          }
        }
      },
      "warning": {
        "filled": {
          "background-color": {
            "attributes": {
              "category": "color"
            },
            "value": "{color.warning.200}"
          },
          "border-color": {
            "attributes": {
              "category": "color"
            },
            "value": "{color.warning.200}"
          },
          "color": {
            "attributes": {
              "category": "color"
            },
            "value": "{color.warning.700}"
          }
        },
        "outlined": {
          "background-color": {
            "attributes": {
              "category": "color"
            },
            "value": "{color.neutral.transparent}"
          },
          "border-color": {
            "attributes": {
              "category": "color"
            },
            "value": "{color.warning.300}"
          },
          "color": {
            "attributes": {
              "category": "color"
            },
            "value": "{color.warning.700}"
          }
        },
        "text": {
          "background-color": {
            "attributes": {
              "category": "color"
            },
            "value": "{color.neutral.transparent}"
          },
          "border-color": {
            "attributes": {
              "category": "color"
            },
            "value": "{color.neutral.transparent}"
          },
          "color": {
            "attributes": {
              "category": "color"
            },
            "value": "{color.warning.700}"
          }
        }
      }
    },
    "size": {
      "default": {
        "height": {
          "attributes": {
            "type": "number"
          },
          "value": "{sizing.40}"
        },
        "spacing": {
          "with-icon-left": {
            "padding-top": {
              "attributes": {
                "type": "spacing"
              },
              "value": "{spacing.12}"
            },
            "padding-right": {
              "attributes": {
                "type": "spacing"
              },
              "value": "{spacing.12}"
            },
            "gap": {
              "attributes": {
                "type": "spacing"
              },
              "value": "{spacing.8}"
            },
            "padding-left": {
              "attributes": {
                "type": "spacing"
              },
              "value": "{spacing.10}"
            },
            "padding-bottom": {
              "attributes": {
                "type": "spacing"
              },
              "value": "{spacing.12}"
            }
          },
          "padding-top": {
            "attributes": {
              "type": "spacing"
            },
            "value": "{spacing.12}"
          },
          "padding-right": {
            "attributes": {
              "type": "spacing"
            },
            "value": "{spacing.12}"
          },
          "padding-left": {
            "attributes": {
              "type": "spacing"
            },
            "value": "{spacing.12}"
          },
          "padding-bottom": {
            "attributes": {
              "type": "spacing"
            },
            "value": "{spacing.12}"
          },
          "gap": {
            "attributes": {
              "type": "spacing"
            },
            "value": "{spacing.8}"
          },
          "with-icon-right": {
            "gap": {
              "attributes": {
                "type": "spacing"
              },
              "value": "{spacing.8}"
            },
            "padding-top": {
              "attributes": {
                "type": "spacing"
              },
              "value": "{spacing.12}"
            },
            "padding-right": {
              "attributes": {
                "type": "spacing"
              },
              "value": "{spacing.10}"
            },
            "padding-left": {
              "attributes": {
                "type": "spacing"
              },
              "value": "{spacing.12}"
            },
            "padding-bottom": {
              "attributes": {
                "type": "spacing"
              },
              "value": "{spacing.12}"
            }
          }
        },
        "font-size": {
          "attributes": {
            "type": "font-size"
          },
          "value": "{fontSize.14}"
        },
        "line-height": {
          "attributes": {
            "type": "line-height"
          },
          "value": "{lineHeight.150}"
        },
        "font-weight": {
          "attributes": {
            "type": "font-weight"
          },
          "value": "{fontWeight.400}"
        },
        "border-radius": {
          "attributes": {
            "type": "border-radius"
          },
          "value": "{borderRadius.4}"
        },
        "border-width": {
          "attributes": {
            "type": "border-width"
          },
          "value": "{borderWidth.1}"
        }
      },
      "sm": {
        "height": {
          "attributes": {
            "type": "number"
          },
          "value": "{sizing.32}"
        },
        "spacing": {
          "with-icon-left": {
            "padding-top": {
              "attributes": {
                "type": "spacing"
              },
              "value": "{spacing.12}"
            },
            "padding-right": {
              "attributes": {
                "type": "spacing"
              },
              "value": "{spacing.12}"
            },
            "padding-left": {
              "attributes": {
                "type": "spacing"
              },
              "value": "{spacing.10}"
            },
            "padding-bottom": {
              "attributes": {
                "type": "spacing"
              },
              "value": "{spacing.12}"
            },
            "gap": {
              "attributes": {
                "type": "spacing"
              },
              "value": "{spacing.8}"
            }
          },
          "padding-top": {
            "attributes": {
              "type": "spacing"
            },
            "value": "{spacing.12}"
          },
          "padding-right": {
            "attributes": {
              "type": "spacing"
            },
            "value": "{spacing.12}"
          },
          "padding-left": {
            "attributes": {
              "type": "spacing"
            },
            "value": "{spacing.12}"
          },
          "padding-bottom": {
            "attributes": {
              "type": "spacing"
            },
            "value": "{spacing.12}"
          },
          "gap": {
            "attributes": {
              "type": "spacing"
            },
            "value": "{spacing.8}"
          },
          "with-icon-right": {
            "padding-top": {
              "attributes": {
                "type": "spacing"
              },
              "value": "{spacing.12}"
            },
            "padding-right": {
              "attributes": {
                "type": "spacing"
              },
              "value": "{spacing.10}"
            },
            "padding-left": {
              "attributes": {
                "type": "spacing"
              },
              "value": "{spacing.12}"
            },
            "padding-bottom": {
              "attributes": {
                "type": "spacing"
              },
              "value": "{spacing.12}"
            },
            "gap": {
              "attributes": {
                "type": "spacing"
              },
              "value": "{spacing.8}"
            }
          }
        },
        "font-size": {
          "attributes": {
            "type": "font-size"
          },
          "value": "{fontSize.14}"
        },
        "line-height": {
          "attributes": {
            "type": "line-height"
          },
          "value": "{lineHeight.150}"
        },
        "font-weight": {
          "attributes": {
            "type": "font-weight"
          },
          "value": "{fontWeight.500}"
        },
        "border-radius": {
          "attributes": {
            "type": "border-radius"
          },
          "value": "{borderRadius.4}"
        },
        "border-width": {
          "attributes": {
            "type": "border-width"
          },
          "value": "{borderWidth.1}"
        }
      },
      "xs": {
        "height": {
          "attributes": {
            "type": "number"
          },
          "value": "{sizing.24}"
        },
        "spacing": {
          "with-icon-left": {
            "padding-top": {
              "attributes": {
                "type": "spacing"
              },
              "value": "{spacing.10}"
            },
            "padding-right": {
              "attributes": {
                "type": "spacing"
              },
              "value": "{spacing.10}"
            },
            "padding-left": {
              "attributes": {
                "type": "spacing"
              },
              "value": "{spacing.8}"
            },
            "padding-bottom": {
              "attributes": {
                "type": "spacing"
              },
              "value": "{spacing.10}"
            },
            "gap": {
              "attributes": {
                "type": "spacing"
              },
              "value": "{spacing.4}"
            }
          },
          "padding-top": {
            "attributes": {
              "type": "spacing"
            },
            "value": "{spacing.10}"
          },
          "padding-right": {
            "attributes": {
              "type": "spacing"
            },
            "value": "{spacing.10}"
          },
          "padding-left": {
            "attributes": {
              "type": "spacing"
            },
            "value": "{spacing.10}"
          },
          "padding-bottom": {
            "attributes": {
              "type": "spacing"
            },
            "value": "{spacing.10}"
          },
          "gap": {
            "attributes": {
              "type": "spacing"
            },
            "value": "{spacing.8}"
          },
          "with-icon-right": {
            "padding-top": {
              "attributes": {
                "type": "spacing"
              },
              "value": "{spacing.10}"
            },
            "padding-right": {
              "attributes": {
                "type": "spacing"
              },
              "value": "{spacing.8}"
            },
            "padding-left": {
              "attributes": {
                "type": "spacing"
              },
              "value": "{spacing.10}"
            },
            "padding-bottom": {
              "attributes": {
                "type": "spacing"
              },
              "value": "{spacing.10}"
            },
            "gap": {
              "attributes": {
                "type": "spacing"
              },
              "value": "{spacing.4}"
            }
          }
        },
        "font-size": {
          "attributes": {
            "type": "font-size"
          },
          "value": "{fontSize.10}"
        },
        "line-height": {
          "attributes": {
            "type": "line-height"
          },
          "value": "{lineHeight.150}"
        },
        "font-weight": {
          "attributes": {
            "type": "font-weight"
          },
          "value": "{fontWeight.500}"
        },
        "border-radius": {
          "attributes": {
            "type": "border-radius"
          },
          "value": "{borderRadius.4}"
        },
        "border-width": {
          "attributes": {
            "type": "border-width"
          },
          "value": "{borderWidth.1}"
        }
      }
    }
  },
  "Number": {
    "attributes": {
      "type": "number"
    },
    "value": 0
  }
}
